opentelemetry/instrumentation/openai/__init__.py
opentelemetry/instrumentation/openai/utils.py
opentelemetry/instrumentation/openai/version.py
opentelemetry/instrumentation/openai/shared/__init__.py
opentelemetry/instrumentation/openai/shared/chat_wrappers.py
opentelemetry/instrumentation/openai/shared/completion_wrappers.py
opentelemetry/instrumentation/openai/shared/config.py
opentelemetry/instrumentation/openai/shared/embeddings_wrappers.py
opentelemetry/instrumentation/openai/shared/event_emitter.py
opentelemetry/instrumentation/openai/shared/event_models.py
opentelemetry/instrumentation/openai/shared/image_gen_wrappers.py
opentelemetry/instrumentation/openai/shared/span_utils.py
opentelemetry/instrumentation/openai/v0/__init__.py
opentelemetry/instrumentation/openai/v1/__init__.py
opentelemetry/instrumentation/openai/v1/assistant_wrappers.py
opentelemetry/instrumentation/openai/v1/event_handler_wrapper.py
opentelemetry/instrumentation/openai/v1/realtime_wrappers.py
opentelemetry/instrumentation/openai/v1/responses_wrappers.py
opentelemetry_instrumentation_openai-0.51.1.dist-info/METADATA
opentelemetry_instrumentation_openai-0.51.1.dist-info/WHEEL
opentelemetry_instrumentation_openai-0.51.1.dist-info/entry_points.txt
opentelemetry_instrumentation_openai-0.51.1.dist-info/RECORD
